[
    {
        "inputs": [],
        "name": "ModelAlreadyExists",
        "type": "error"
    },
    {
        "anonymous": false,
        "inputs": [
            {
                "indexed": true,
                "internalType": "bytes32",
                "name": "modelId",
                "type": "bytes32"
            },
            {
                "indexed": false,
                "internalType": "string",
                "name": "metadata",
                "type": "string"
            }
        ],
        "name": "ModelSubmitted",
        "type": "event"
    },
    {
        "inputs": [
            {
                "internalType": "bytes32",
                "name": "modelId",
                "type": "bytes32"
            }
        ],
        "name": "getProof",
        "outputs": [
            {
                "internalType": "string",
                "name": "",
                "type": "string"
            }
        ],
        "stateMutability": "view",
        "type": "function"
    },
    {
        "inputs": [
            {
                "internalType": "bytes32",
                "name": "modelId",
                "type": "bytes32"
            },
            {
                "internalType": "string",
                "name": "metadata",
                "type": "string"
            }
        ],
        "name": "submitProof",
        "outputs": [],
        "stateMutability": "nonpayable",
        "type": "function"
    }
]
